skrbcr_casa_scripts/Image.py
skrbcr_casa_scripts/PlotConfig.py
skrbcr_casa_scripts/__init__.py
skrbcr_casa_scripts/azimuthal_cut.py
skrbcr_casa_scripts/detectpeak.py
skrbcr_casa_scripts/imshow.py
skrbcr_casa_scripts/imstat.py
skrbcr_casa_scripts/matplotlib_helper.py
skrbcr_casa_scripts/prepare_image.py
skrbcr_casa_scripts/radial_cut.py
skrbcr_casa_scripts/radial_profile.py
skrbcr_casa_scripts/utilities.py
skrbcr_casa_scripts-1.0.2.dist-info/LICENSE
skrbcr_casa_scripts-1.0.2.dist-info/METADATA
skrbcr_casa_scripts-1.0.2.dist-info/WHEEL
skrbcr_casa_scripts-1.0.2.dist-info/top_level.txt
skrbcr_casa_scripts-1.0.2.dist-info/RECORD
